{"nm":"Main Scene","h":1080,"w":1080,"meta":{"g":"@lottiefiles/creator 1.75.0"},"layers":[{"ty":4,"nm":"G","sr":1,"st":0,"op":50,"ip":0,"hasMask":false,"ao":0,"ks":{"a":{"a":0,"k":[541.559,539.732,0]},"s":{"a":0,"k":[1691,1691,100]},"sk":{"a":0,"k":0},"p":{"a":1,"k":[{"o":{"x":0.333,"y":0},"i":{"x":0.667,"y":1},"s":[629.614,540],"t":0},{"o":{"x":0.333,"y":0},"i":{"x":0.667,"y":1},"s":[505.614,540,0],"t":8.333,"ti":[-20.667,0,0],"to":[-3.833,0,0]},{"o":{"x":0.333,"y":0},"i":{"x":0.667,"y":1},"s":[606.614,540,0],"t":16.667,"ti":[0,0,0],"to":[20.667,0,0]},{"o":{"x":0.333,"y":0},"i":{"x":0.667,"y":1},"s":[629.614,540,0],"t":25,"ti":[3.833,0,0],"to":[-20.667,0,0]},{"o":{"x":0.333,"y":0},"i":{"x":0.667,"y":1},"s":[505.614,540,0],"t":33.333,"ti":[-20.667,0,0],"to":[-3.833,0,0]},{"o":{"x":0.333,"y":0},"i":{"x":0.667,"y":1},"s":[606.614,540,0],"t":41.667,"ti":[-3.833,0,0],"to":[20.667,0,0]},{"s":[629.614,540,0],"t":50}]},"r":{"a":0,"k":0},"sa":{"a":0,"k":0},"o":{"a":0,"k":100}},"shapes":[{"ty":"gr","nm":"G","it":[{"ty":"gr","nm":"G","it":[{"ty":"sh","nm":"P","d":1,"ks":{"a":0,"k":{"c":false,"i":[[0,0],[0,0]],"o":[[0,0],[0,0]],"v":[[11.598,0],[-11.598,0]]}}},{"ty":"st","nm":"S","lc":2,"lj":1,"ml":10,"o":{"a":0,"k":100},"w":{"a":0,"k":4},"c":{"a":0,"k":[0.294,0.439,0.922]}},{"ty":"tr","a":{"a":0,"k":[0,0]},"s":{"a":0,"k":[100,100]},"sk":{"a":0,"k":0},"p":{"a":0,"k":[541.557,539.732]},"r":{"a":0,"k":0},"sa":{"a":0,"k":0},"o":{"a":0,"k":100}}]},{"ty":"gr","nm":"G","it":[{"ty":"sh","nm":"P","d":1,"ks":{"a":0,"k":{"c":false,"i":[[0,0],[0,0],[0,0]],"o":[[0,0],[0,0],[0,0]],"v":[[-3.536,7.464],[3.536,0],[-3.536,-7.464]]}}},{"ty":"st","nm":"S","lc":2,"lj":1,"ml":10,"o":{"a":0,"k":100},"w":{"a":0,"k":4},"c":{"a":0,"k":[0.294,0.439,0.922]}},{"ty":"tr","a":{"a":0,"k":[0,0]},"s":{"a":0,"k":[100,100]},"sk":{"a":0,"k":0},"p":{"a":0,"k":[549.622,539.732]},"r":{"a":0,"k":0},"sa":{"a":0,"k":0},"o":{"a":0,"k":100}}]},{"ty":"tr","a":{"a":0,"k":[549.622,539.732]},"s":{"a":0,"k":[100,100]},"sk":{"a":0,"k":0},"p":{"a":0,"k":[549.622,539.732]},"r":{"a":0,"k":0},"sa":{"a":0,"k":0},"o":{"a":0,"k":100}}]}],"ind":1},{"ty":4,"nm":"G","sr":1,"st":0,"op":50,"ip":0,"hasMask":false,"ao":0,"ks":{"a":{"a":0,"k":[525.336,539.732,0]},"s":{"a":0,"k":[1691,1691,100]},"sk":{"a":0,"k":0},"p":{"a":0,"k":[329.301,540]},"r":{"a":0,"k":0},"sa":{"a":0,"k":0},"o":{"a":0,"k":100}},"shapes":[{"ty":"gr","nm":"G","it":[{"ty":"sh","nm":"P","d":1,"ks":{"a":0,"k":{"c":false,"i":[[0,0],[0,-3.205],[0,0],[-3.205,0]],"o":[[-3.205,0],[0,0],[0,3.205],[0,0]],"v":[[2.901,-17],[-2.901,-11.197],[-2.901,11.197],[2.901,17]]}}},{"ty":"st","nm":"S","lc":2,"lj":1,"ml":10,"o":{"a":0,"k":100},"w":{"a":0,"k":4},"c":{"a":0,"k":[0.294,0.439,0.922]}},{"ty":"tr","a":{"a":0,"k":[0,0]},"s":{"a":0,"k":[100,100]},"sk":{"a":0,"k":0},"p":{"a":0,"k":[525.336,539.732]},"r":{"a":0,"k":0},"sa":{"a":0,"k":0},"o":{"a":0,"k":100}}]}],"ind":2}],"v":"5.7.0","fr":25,"op":50,"ip":0,"assets":[]}